all_label_converter/__init__.py
all_label_converter/commonformat.py
all_label_converter/config.yaml
all_label_converter/cores/__init__.py
all_label_converter/cores/coco_type.py
all_label_converter/cores/config.py
all_label_converter/cores/createml_type.py
all_label_converter/cores/tfcsv_type.py
all_label_converter/cores/utils.py
all_label_converter/cores/voc_type.py
all_label_converter/cores/yolodarknet_type.py
all_label_converter-0.1.7.dist-info/LICENSE
all_label_converter-0.1.7.dist-info/METADATA
all_label_converter-0.1.7.dist-info/WHEEL
all_label_converter-0.1.7.dist-info/top_level.txt
all_label_converter-0.1.7.dist-info/RECORD
