Metadata-Version: 2.1
Name: all-label-converter
Version: 0.1.7
Summary: To convert image labels between each other.
Home-page: https://github.com/fatihb7/all_label_converter
Author: Fatih Baday
Author-email: bfatih27@gmail.com
License: UNKNOWN
Platform: UNKNOWN
Classifier: Programming Language :: Python :: 3
Requires-Python: >=3.6.0
License-File: LICENSE
Requires-Dist: certifi (==2020.12.5)
Requires-Dist: opencv-python (>=4.5)
Requires-Dist: pandas (>=1.3)
Requires-Dist: python-dateutil (==2.8.2)
Requires-Dist: pytz (==2021.1)
Requires-Dist: six (==1.16.0)
Requires-Dist: wincertstore (==0.2)
Requires-Dist: pyyaml (==5.4.1)
